lazybids/__init__.py
lazybids/connection.py
lazybids/datatypes.py
lazybids/resources/itk_supported_extensions.json
lazybids/resources/schema/BIDS_VERSION
lazybids/resources/schema/README.md
lazybids/resources/schema/SCHEMA_VERSION
lazybids/resources/schema/meta/associations.yaml
lazybids/resources/schema/meta/context.yaml
lazybids/resources/schema/meta/expression_tests.yaml
lazybids/resources/schema/meta/versions.yaml
lazybids/resources/schema/objects/columns.yaml
lazybids/resources/schema/objects/common_principles.yaml
lazybids/resources/schema/objects/datatypes.yaml
lazybids/resources/schema/objects/entities.yaml
lazybids/resources/schema/objects/enums.yaml
lazybids/resources/schema/objects/extensions.yaml
lazybids/resources/schema/objects/files.yaml
lazybids/resources/schema/objects/formats.yaml
lazybids/resources/schema/objects/metadata.yaml
lazybids/resources/schema/objects/modalities.yaml
lazybids/resources/schema/objects/suffixes.yaml
lazybids/resources/schema/rules/checks/anat.yaml
lazybids/resources/schema/rules/checks/asl.yaml
lazybids/resources/schema/rules/checks/common_derivatives.yaml
lazybids/resources/schema/rules/checks/dataset.yaml
lazybids/resources/schema/rules/checks/dwi.yaml
lazybids/resources/schema/rules/checks/events.yaml
lazybids/resources/schema/rules/checks/fmap.yaml
lazybids/resources/schema/rules/checks/func.yaml
lazybids/resources/schema/rules/checks/general.yaml
lazybids/resources/schema/rules/checks/hints.yaml
lazybids/resources/schema/rules/checks/micr.yaml
lazybids/resources/schema/rules/checks/mri.yaml
lazybids/resources/schema/rules/checks/nifti.yaml
lazybids/resources/schema/rules/checks/nirs.yaml
lazybids/resources/schema/rules/checks/privacy.yaml
lazybids/resources/schema/rules/checks/references.yaml
lazybids/resources/schema/rules/common_principles.yaml
lazybids/resources/schema/rules/dataset_metadata.yaml
lazybids/resources/schema/rules/entities.yaml
lazybids/resources/schema/rules/errors.yaml
lazybids-0.2.1.dist-info/LICENSE
lazybids-0.2.1.dist-info/METADATA
lazybids-0.2.1.dist-info/WHEEL
lazybids-0.2.1.dist-info/RECORD
