Metadata-Version: 2.1
Name: lazybids
Version: 0.2.1
Summary: lazybids is a python package that helps interact with existing bids datasets and convert existing dicom or nifti datasets to BIDS.
Author: Roelant
Author-email: roelanteijgelaar@hotmail.com
Requires-Python: >=3.8,<3.13
Classifier: Programming Language :: Python :: 3
Classifier: Programming Language :: Python :: 3.8
Classifier: Programming Language :: Python :: 3.9
Classifier: Programming Language :: Python :: 3.10
Classifier: Programming Language :: Python :: 3.11
Classifier: Programming Language :: Python :: 3.12
Requires-Dist: h5py (>=3.10.0,<4.0.0)
Requires-Dist: pandas (>=2.0.0,<3.0.0)
Requires-Dist: pydantic (>=2.5.2,<3.0.0)
Requires-Dist: pydicom (>=2.4.3,<3.0.0)
Requires-Dist: pyyaml (>=6.0.1,<7.0.0)
Requires-Dist: rich (>=13.7.0,<14.0.0)
Requires-Dist: simpleitk (>=2.3.1,<3.0.0)
Requires-Dist: tqdm (>=4.66.1,<5.0.0)
